.gitignore
README.markdown
setup.py
todo
wag/__init__.py
wag/filters.py
wag/shell.py
wag/templates.py
wag/wag.py
wag.egg-info/PKG-INFO
wag.egg-info/SOURCES.txt
wag.egg-info/dependency_links.txt
wag.egg-info/entry_points.txt
wag.egg-info/not-zip-safe
wag.egg-info/requires.txt
wag.egg-info/top_level.txt
wag/data/default_rss_template