Metadata-Version: 1.0
Name: wag
Version: 0.4
Summary: Tail your rss and atom feeds
Home-page: http://github.com/knobe/wag/tree/master
Author: Tyler Harper
Author-email: tyler.a.harper@gmail.com
License: UNKNOWN
Platform: UNKNOWN
Classifier: Development Status :: 3 - Alpha
Classifier: Environment :: Console
Classifier: Intended Audience :: Developers
Classifier: License :: OSI Approved :: BSD License
Classifier: Programming Language :: Python
